eidolon_ai_client/__init__.py
eidolon_ai_client/cli.py
eidolon_ai_client/client.py
eidolon_ai_client/events.py
eidolon_ai_client/group_conversation.py
eidolon_ai_client/util/__init__.py
eidolon_ai_client/util/aiohttp.py
eidolon_ai_client/util/logger.py
eidolon_ai_client/util/request_context.py
eidolon_ai_client/util/stream_collector.py
eidolon_ai_client-0.1.40.dist-info/METADATA
eidolon_ai_client-0.1.40.dist-info/WHEEL
eidolon_ai_client-0.1.40.dist-info/entry_points.txt
eidolon_ai_client-0.1.40.dist-info/RECORD
